{
        "metadata": {
                "title": "OPDS 2.0 Test Catalog"
        },
        "links": [
                {
                        "rel": "self",
                        "href": "https://test.opds.io/2.0/home.json",
                        "type": "application/opds+json"
                }
        ],
        "navigation": [
                {
                        "href": "https://test.opds.io/2.0/navigation.json",
                        "title": "Explore (Navigation Feed)",
                        "type": "application/opds+json"
                },
                {
                        "href": "https://test.opds.io/2.0/publications.json",
                        "title": "French Books (Publications Feed)",
                        "type": "application/opds+json"
                },
                {
                        "href": "https://test.opds.io/2.0/home.json",
                        "title": "Third Link",
                        "type": "application/opds+json"
                }
        ]

}